ttytables/__init__.py
ttytables/table.py
ttytables-0.0.1.dist-info/LICENSE
ttytables-0.0.1.dist-info/METADATA
ttytables-0.0.1.dist-info/WHEEL
ttytables-0.0.1.dist-info/top_level.txt
ttytables-0.0.1.dist-info/RECORD
